t11p_h/__init__.py
t11p_h/main.py
t11p_h/AddressBook/Address_Book_Handler.py
t11p_h/AddressBook/addressbook.py
t11p_h/AddressBook/addressbook_data.py
t11p_h/GameGooseKiller/Game_goose.py
t11p_h/GameGooseKiller/font/UA Propisi.ttf
t11p_h/GameGooseKiller/image/Farm-Goose.ico
t11p_h/GameGooseKiller/image/background.png
t11p_h/GameGooseKiller/image/bonus.png
t11p_h/GameGooseKiller/image/boom.png
t11p_h/GameGooseKiller/image/enemy.png
t11p_h/GameGooseKiller/image/gameover.png
t11p_h/GameGooseKiller/image/Goose/1-1.png
t11p_h/GameGooseKiller/image/Goose/1-2.png
t11p_h/GameGooseKiller/image/Goose/1-3.png
t11p_h/GameGooseKiller/image/Goose/1-4.png
t11p_h/GameGooseKiller/image/Goose/1-5.png
t11p_h/GameGooseKiller/image/background/1-1.png
t11p_h/GameGooseKiller/image/background/1-2.png
t11p_h/GameGooseKiller/image/background/1-3.png
t11p_h/NoteBook/Note.py
t11p_h/NoteBook/Note_Book_Handler.py
t11p_h/OtherModules/Sort_Files.py
t11p_h/OtherModules/Сalculator.py
t11p_h-1.0.0.data/data/t11p_h/GameGooseKiller/font/UA Propisi.ttf
t11p_h-1.0.0.data/data/t11p_h/GameGooseKiller/image/Farm-Goose.ico
t11p_h-1.0.0.data/data/t11p_h/GameGooseKiller/image/background.png
t11p_h-1.0.0.data/data/t11p_h/GameGooseKiller/image/bonus.png
t11p_h-1.0.0.data/data/t11p_h/GameGooseKiller/image/boom.png
t11p_h-1.0.0.data/data/t11p_h/GameGooseKiller/image/enemy.png
t11p_h-1.0.0.data/data/t11p_h/GameGooseKiller/image/gameover.png
t11p_h-1.0.0.data/data/t11p_h/GameGooseKiller/image/Goose/1-1.png
t11p_h-1.0.0.data/data/t11p_h/GameGooseKiller/image/Goose/1-2.png
t11p_h-1.0.0.data/data/t11p_h/GameGooseKiller/image/Goose/1-3.png
t11p_h-1.0.0.data/data/t11p_h/GameGooseKiller/image/Goose/1-4.png
t11p_h-1.0.0.data/data/t11p_h/GameGooseKiller/image/Goose/1-5.png
t11p_h-1.0.0.data/data/t11p_h/GameGooseKiller/image/background/1-1.png
t11p_h-1.0.0.data/data/t11p_h/GameGooseKiller/image/background/1-2.png
t11p_h-1.0.0.data/data/t11p_h/GameGooseKiller/image/background/1-3.png
t11p_h-1.0.0.dist-info/LICENSE
t11p_h-1.0.0.dist-info/METADATA
t11p_h-1.0.0.dist-info/WHEEL
t11p_h-1.0.0.dist-info/entry_points.txt
t11p_h-1.0.0.dist-info/top_level.txt
t11p_h-1.0.0.dist-info/RECORD
